{
    "@context": "https://schema.org",
    "@type": "CreativeWork",
    "@id": "https://heritage.tudelft.nl/iiif/manifests/95499e2d-d517-4c12-899c-83e2d7c3e8ce/schema.json",
    "name": "Leren aktetas van college van curatoren.",
    "description": "Deze aktetas werd van 1905 tot 1971 gebruikt door het college van curatoren.\nMet de overgang van Polytechnische School naar de Technische Hoogeschool in 1905 kwam het bestuur in handen van het college van curatoren en de senaat. De curatoren waren belast met de zorg voor de huisvesting en het beheer van de financiën. De senaat, die bestond uit alle ‘gewone’ hoogleraren, behartigde het belang van het onderwijs en de wetenschap. \nIn 1971 werd de Wet Universitaire Bestuurshervorming ingevoerd, bedoeld om de oude, starre, bestuursstructuur te doorbreken zodat er makkelijker op maatschappelijke veranderingen ingesprongen kon worden. Het bestuur van de universiteit veranderde daarmee ingrijpend. Dit betekende het einde van het college van curatoren en daarmee het einde van het gebruik van deze aktetas.",
    "identifier": "1992.0257.TMD",
    "temporalCoverage": "1905/1971",
    "exampleOfWork": {
        "@type": "CreativeWork",
        "name": "aktetas"
    },
    "material": {
        "@type": "Product",
        "name": "leer"
    },
    "contributor": {
        "@type": "Role",
        "roleName": "had in bezit",
        "contributor": {
            "@type": "Organization",
            "name": "College van  Curatoren"
        }
    },
    "height": {
        "@type": "QuantitativeValue",
        "unitCode": "MMT",
        "value": 400
    },
    "width": {
        "@type": "QuantitativeValue",
        "unitCode": "MMT",
        "value": 420
    },
    "depth": {
        "@type": "QuantitativeValue",
        "unitCode": "MMT",
        "value": 130
    },
    "image": {
        "@type": "ImageObject",
        "contentUrl": {
            "@context": "http://iiif.io/api/presentation/3/context.json",
            "@id": "https://dlc.services/iiif-img/7/18/61d8907c-7c3f-47ae-9856-ba5ba9ebf9fa",
            "@type": "Image"
        },
        "thumbnailUrl": "https://dlc.services/thumbs/7/18/61d8907c-7c3f-47ae-9856-ba5ba9ebf9fa/full/full/0/default.jpg",
        "encodingFormat": "https://iiif.io/api/image/3.0/",
        "caption": "1992.0257.TMD.JPG",
        "width": 1600,
        "height": 1200,
        "position": 6535
    }
}