{
    "@context": "http://iiif.io/api/presentation/3/context.json",
    "id": "https://tu-delft-heritage.github.io/collective-access-data/iiif/objects/8522b3b0-9cc5-46d7-9255-f46f28dc2a02.json",
    "type": "Manifest",
    "label": {
        "nl": [
            "Driepoot statief voor équerre of een Hollandse cirkel door Gebrüder Fromme"
        ]
    },
    "metadata": [
        {
            "label": {
                "en": [
                    "Title"
                ],
                "nl": [
                    "Titel"
                ]
            },
            "value": {
                "nl": [
                    "Driepoot statief voor équerre of een Hollandse cirkel door Gebrüder Fromme"
                ]
            }
        },
        {
            "label": {
                "en": [
                    "Object name"
                ],
                "nl": [
                    "Objectnaam"
                ]
            },
            "value": {
                "nl": [
                    "statief (standaarden)"
                ]
            }
        },
        {
            "label": {
                "en": [
                    "Inventory number"
                ],
                "nl": [
                    "Inventarisnummer"
                ]
            },
            "value": {
                "nl": [
                    "2000.0544.GEO"
                ]
            }
        },
        {
            "label": {
                "en": [
                    "Dating"
                ],
                "nl": [
                    "Datering"
                ]
            },
            "value": {
                "nl": [
                    "1875 – 1900"
                ]
            }
        },
        {
            "label": {
                "en": [
                    "Maker"
                ],
                "nl": [
                    "Maker"
                ]
            },
            "value": {
                "nl": [
                    "Gebrüder Fromme   (producent)"
                ]
            }
        },
        {
            "label": {
                "en": [
                    "Dimensions"
                ],
                "nl": [
                    "Afmetingen"
                ]
            },
            "value": {
                "nl": [
                    "1.410,0 mm (h) x 580,0 mm (b) x 580,0 mm (d)"
                ]
            }
        },
        {
            "label": {
                "en": [
                    "Material"
                ],
                "nl": [
                    "Materiaal"
                ]
            },
            "value": {
                "nl": [
                    "hout",
                    "koper",
                    "ijzer"
                ]
            }
        },
        {
            "label": {
                "en": [
                    "Place of manufacture"
                ],
                "nl": [
                    "Plaats vervaardiging"
                ]
            },
            "value": {
                "nl": [
                    "<a href=\"https://www.geonames.org/2761369\">Wenen, Oostenrijk</a>"
                ]
            }
        },
        {
            "label": {
                "en": [
                    "Description"
                ],
                "nl": [
                    "Beschrijving"
                ]
            },
            "value": {
                "nl": [
                    "Driepoot statief voor het plaatsen van geodetisch instrument met kogelgewricht zoals een equerre of Hollandse cirkel, door Gebrüder Fromme, door een ingenieuze constructie kan de verticale as heel precies verticaal gesteld worden. Voor bijvoorbeeld de Hollandse cirkel onder inventarisnummer 2000.0043.GEO."
                ]
            }
        },
        {
            "label": {
                "en": [
                    "Related object"
                ],
                "nl": [
                    "Gerelateerd object"
                ]
            },
            "value": {
                "nl": [
                    "Hollandse cirkel door R. Konst (GEO.2000.0043)"
                ]
            }
        }
    ],
    "navDate": "1875-01-01T00:00:00.000Z",
    "thumbnail": [
        {
            "id": "https://dlc.services/thumbs/v3/7/18/56779549-d08c-4bf7-b790-3631bcad74f1/full/max/0/default.jpg",
            "type": "Image",
            "format": "image/jpeg",
            "service": [
                {
                    "@context": "http://iiif.io/api/image/3/context.json",
                    "id": "https://dlc.services/thumbs/v3/7/18/56779549-d08c-4bf7-b790-3631bcad74f1",
                    "type": "ImageService3",
                    "profile": "level0",
                    "sizes": [
                        {
                            "width": 1024,
                            "height": 592
                        },
                        {
                            "width": 400,
                            "height": 231
                        },
                        {
                            "width": 200,
                            "height": 116
                        },
                        {
                            "width": 100,
                            "height": 58
                        }
                    ]
                }
            ]
        }
    ],
    "items": [
        {
            "id": "https://tu-delft-heritage.github.io/collective-access-data/iiif/objects/8522b3b0-9cc5-46d7-9255-f46f28dc2a02/canvas/0",
            "type": "Canvas",
            "height": 1776,
            "width": 3072,
            "thumbnail": [
                {
                    "id": "https://dlc.services/thumbs/v3/7/18/56779549-d08c-4bf7-b790-3631bcad74f1/full/max/0/default.jpg",
                    "type": "Image",
                    "format": "image/jpeg",
                    "service": [
                        {
                            "@context": "http://iiif.io/api/image/3/context.json",
                            "id": "https://dlc.services/thumbs/v3/7/18/56779549-d08c-4bf7-b790-3631bcad74f1",
                            "type": "ImageService3",
                            "profile": "level0",
                            "sizes": [
                                {
                                    "width": 1024,
                                    "height": 592
                                },
                                {
                                    "width": 400,
                                    "height": 231
                                },
                                {
                                    "width": 200,
                                    "height": 116
                                },
                                {
                                    "width": 100,
                                    "height": 58
                                }
                            ]
                        }
                    ]
                }
            ],
            "items": [
                {
                    "id": "https://tu-delft-heritage.github.io/collective-access-data/iiif/objects/8522b3b0-9cc5-46d7-9255-f46f28dc2a02/canvas/0/annotation-page",
                    "type": "AnnotationPage",
                    "items": [
                        {
                            "id": "https://dlc.services/iiif-img/v3/7/18/56779549-d08c-4bf7-b790-3631bcad74f1",
                            "type": "Annotation",
                            "motivation": "painting",
                            "target": "https://tu-delft-heritage.github.io/collective-access-data/iiif/objects/8522b3b0-9cc5-46d7-9255-f46f28dc2a02/canvas/0",
                            "body": {
                                "id": "https://dlc.services/iiif-img/v3/7/18/56779549-d08c-4bf7-b790-3631bcad74f1/full/max/0/default.jpg",
                                "type": "Image",
                                "format": "image/jpeg",
                                "height": 1776,
                                "width": 3072,
                                "service": [
                                    {
                                        "@context": "http://iiif.io/api/image/3/context.json",
                                        "id": "https://dlc.services/iiif-img/v3/7/18/56779549-d08c-4bf7-b790-3631bcad74f1",
                                        "type": "ImageService3",
                                        "profile": "level2"
                                    }
                                ]
                            }
                        }
                    ]
                }
            ]
        },
        {
            "id": "https://tu-delft-heritage.github.io/collective-access-data/iiif/objects/8522b3b0-9cc5-46d7-9255-f46f28dc2a02/canvas/1",
            "type": "Canvas",
            "height": 3072,
            "width": 2048,
            "thumbnail": [
                {
                    "id": "https://dlc.services/thumbs/v3/7/18/05e1f60e-548b-4c5a-8642-36e61310f9fa/full/max/0/default.jpg",
                    "type": "Image",
                    "format": "image/jpeg",
                    "service": [
                        {
                            "@context": "http://iiif.io/api/image/3/context.json",
                            "id": "https://dlc.services/thumbs/v3/7/18/05e1f60e-548b-4c5a-8642-36e61310f9fa",
                            "type": "ImageService3",
                            "profile": "level0",
                            "sizes": [
                                {
                                    "width": 683,
                                    "height": 1024
                                },
                                {
                                    "width": 267,
                                    "height": 400
                                },
                                {
                                    "width": 133,
                                    "height": 200
                                },
                                {
                                    "width": 67,
                                    "height": 100
                                }
                            ]
                        }
                    ]
                }
            ],
            "items": [
                {
                    "id": "https://tu-delft-heritage.github.io/collective-access-data/iiif/objects/8522b3b0-9cc5-46d7-9255-f46f28dc2a02/canvas/1/annotation-page",
                    "type": "AnnotationPage",
                    "items": [
                        {
                            "id": "https://dlc.services/iiif-img/v3/7/18/05e1f60e-548b-4c5a-8642-36e61310f9fa",
                            "type": "Annotation",
                            "motivation": "painting",
                            "target": "https://tu-delft-heritage.github.io/collective-access-data/iiif/objects/8522b3b0-9cc5-46d7-9255-f46f28dc2a02/canvas/1",
                            "body": {
                                "id": "https://dlc.services/iiif-img/v3/7/18/05e1f60e-548b-4c5a-8642-36e61310f9fa/full/max/0/default.jpg",
                                "type": "Image",
                                "format": "image/jpeg",
                                "height": 3072,
                                "width": 2048,
                                "service": [
                                    {
                                        "@context": "http://iiif.io/api/image/3/context.json",
                                        "id": "https://dlc.services/iiif-img/v3/7/18/05e1f60e-548b-4c5a-8642-36e61310f9fa",
                                        "type": "ImageService3",
                                        "profile": "level2"
                                    }
                                ]
                            }
                        }
                    ]
                }
            ]
        }
    ]
}