{
    "@context": "http://iiif.io/api/presentation/3/context.json",
    "id": "https://tu-delft-heritage.github.io/collective-access-data/iiif/objects/fabb1d6b-b32f-4d57-9802-65702c2f4f47.json",
    "type": "Manifest",
    "label": {
        "nl": [
            "Holosterische barometer"
        ]
    },
    "metadata": [
        {
            "label": {
                "en": [
                    "Title"
                ],
                "nl": [
                    "Titel"
                ]
            },
            "value": {
                "nl": [
                    "Holosterische barometer"
                ]
            }
        },
        {
            "label": {
                "en": [
                    "Object name"
                ],
                "nl": [
                    "Objectnaam"
                ]
            },
            "value": {
                "nl": [
                    "barometer"
                ]
            }
        },
        {
            "label": {
                "en": [
                    "Inventory number"
                ],
                "nl": [
                    "Inventarisnummer"
                ]
            },
            "value": {
                "nl": [
                    "2011.0010.GEO"
                ]
            }
        },
        {
            "label": {
                "en": [
                    "Dating"
                ],
                "nl": [
                    "Datering"
                ]
            },
            "value": {
                "nl": [
                    "1875 – 1925"
                ]
            }
        },
        {
            "label": {
                "en": [
                    "Dimensions"
                ],
                "nl": [
                    "Afmetingen"
                ]
            },
            "value": {
                "nl": [
                    "165,0 mm (h) x 165,0 mm (b) x 88,0 mm (d)"
                ]
            }
        },
        {
            "label": {
                "en": [
                    "Material"
                ],
                "nl": [
                    "Materiaal"
                ]
            },
            "value": {
                "nl": [
                    "metaal",
                    "hout"
                ]
            }
        },
        {
            "label": {
                "en": [
                    "Description"
                ],
                "nl": [
                    "Beschrijving"
                ]
            },
            "value": {
                "nl": [
                    "Holosterische barometer, stootvast ingebouwd om ermee te kunnen reizen. Barometers waren vooral van belang bij hydrostatische waterpassing en bij hoogtebepalingen in moeilijk toegankelijke gebieden, zoals Borneo en Nieuw Guinea."
                ]
            }
        }
    ],
    "thumbnail": [
        {
            "id": "https://dlc.services/thumbs/v3/7/18/936251d4-fa72-4fac-a4ed-5072b052204e/full/max/0/default.jpg",
            "type": "Image",
            "format": "image/jpeg",
            "service": [
                {
                    "@context": "http://iiif.io/api/image/3/context.json",
                    "id": "https://dlc.services/thumbs/v3/7/18/936251d4-fa72-4fac-a4ed-5072b052204e",
                    "type": "ImageService3",
                    "profile": "level0",
                    "sizes": [
                        {
                            "width": 1024,
                            "height": 784
                        },
                        {
                            "width": 400,
                            "height": 306
                        },
                        {
                            "width": 200,
                            "height": 153
                        },
                        {
                            "width": 100,
                            "height": 77
                        }
                    ]
                }
            ]
        }
    ],
    "items": [
        {
            "id": "https://tu-delft-heritage.github.io/collective-access-data/iiif/objects/fabb1d6b-b32f-4d57-9802-65702c2f4f47/canvas/0",
            "type": "Canvas",
            "height": 1893,
            "width": 2472,
            "thumbnail": [
                {
                    "id": "https://dlc.services/thumbs/v3/7/18/936251d4-fa72-4fac-a4ed-5072b052204e/full/max/0/default.jpg",
                    "type": "Image",
                    "format": "image/jpeg",
                    "service": [
                        {
                            "@context": "http://iiif.io/api/image/3/context.json",
                            "id": "https://dlc.services/thumbs/v3/7/18/936251d4-fa72-4fac-a4ed-5072b052204e",
                            "type": "ImageService3",
                            "profile": "level0",
                            "sizes": [
                                {
                                    "width": 1024,
                                    "height": 784
                                },
                                {
                                    "width": 400,
                                    "height": 306
                                },
                                {
                                    "width": 200,
                                    "height": 153
                                },
                                {
                                    "width": 100,
                                    "height": 77
                                }
                            ]
                        }
                    ]
                }
            ],
            "items": [
                {
                    "id": "https://tu-delft-heritage.github.io/collective-access-data/iiif/objects/fabb1d6b-b32f-4d57-9802-65702c2f4f47/canvas/0/annotation-page",
                    "type": "AnnotationPage",
                    "items": [
                        {
                            "id": "https://dlc.services/iiif-img/v3/7/18/936251d4-fa72-4fac-a4ed-5072b052204e",
                            "type": "Annotation",
                            "motivation": "painting",
                            "target": "https://tu-delft-heritage.github.io/collective-access-data/iiif/objects/fabb1d6b-b32f-4d57-9802-65702c2f4f47/canvas/0",
                            "body": {
                                "id": "https://dlc.services/iiif-img/v3/7/18/936251d4-fa72-4fac-a4ed-5072b052204e/full/max/0/default.jpg",
                                "type": "Image",
                                "format": "image/jpeg",
                                "height": 1893,
                                "width": 2472,
                                "service": [
                                    {
                                        "@context": "http://iiif.io/api/image/3/context.json",
                                        "id": "https://dlc.services/iiif-img/v3/7/18/936251d4-fa72-4fac-a4ed-5072b052204e",
                                        "type": "ImageService3",
                                        "profile": "level2"
                                    }
                                ]
                            }
                        }
                    ]
                }
            ]
        }
    ]
}