{
    "@context": "http://iiif.io/api/presentation/3/context.json",
    "id": "https://tu-delft-heritage.github.io/beeldbank-data/manifests/f997cead-eab1-48d4-b99e-eb5cd2015ab0.json",
    "type": "Manifest",
    "label": {
        "nl": [
            "Aanbieding Almanak D.S.B. in hoofdgebouw TH Delft (1)"
        ]
    },
    "metadata": [
        {
            "label": {
                "en": [
                    "Title"
                ],
                "nl": [
                    "Titel"
                ]
            },
            "value": {
                "nl": [
                    "Aanbieding Almanak D.S.B. in hoofdgebouw TH Delft (1)"
                ]
            }
        },
        {
            "label": {
                "en": [
                    "Description"
                ],
                "nl": [
                    "Beschrijving"
                ]
            },
            "value": {
                "nl": [
                    "Aanbieding van de Almanak van de Delftsche Studenten Bond in het hoofdgebouw van de Technische Hogeschool Delft."
                ]
            }
        },
        {
            "label": {
                "en": [
                    "Year"
                ],
                "nl": [
                    "Jaar"
                ]
            },
            "value": {
                "nl": [
                    "1960-12-23"
                ]
            }
        },
        {
            "label": {
                "en": [
                    "Material"
                ],
                "nl": [
                    "Materiaal"
                ]
            },
            "value": {
                "nl": [
                    "zwart/wit negatief"
                ]
            }
        },
        {
            "label": {
                "en": [
                    "Subject"
                ],
                "nl": [
                    "Onderwerp"
                ]
            },
            "value": {
                "nl": [
                    "studenten",
                    "TU Delft",
                    "evenementen"
                ]
            }
        },
        {
            "label": {
                "en": [
                    "Photographer"
                ],
                "nl": [
                    "Fotograaf"
                ]
            },
            "value": {
                "nl": [
                    "Fotografische Dienst TU Delft"
                ]
            }
        },
        {
            "label": {
                "en": [
                    "Faculty"
                ],
                "nl": [
                    "Faculteit"
                ]
            },
            "value": {
                "nl": [
                    "Delft University of Technology"
                ]
            }
        },
        {
            "label": {
                "en": [
                    "Location"
                ],
                "nl": [
                    "Locatie"
                ]
            },
            "value": {
                "nl": [
                    "Delft"
                ]
            }
        },
        {
            "label": {
                "en": [
                    "Rights"
                ],
                "nl": [
                    "Rechten"
                ]
            },
            "value": {
                "nl": [
                    "(c) Delft University of Technology . Creative Commons BY"
                ]
            }
        }
    ],
    "thumbnail": [
        {
            "id": "https://dlc.services/thumbs/v3/7/15/14d595b6-0f4c-48f7-b381-d7912efe2815/full/max/0/default.jpg",
            "type": "Image",
            "format": "image/jpeg",
            "service": [
                {
                    "@context": "http://iiif.io/api/image/3/context.json",
                    "id": "https://dlc.services/thumbs/v3/7/15/14d595b6-0f4c-48f7-b381-d7912efe2815",
                    "type": "ImageService3",
                    "profile": "level0",
                    "sizes": [
                        {
                            "width": 1024,
                            "height": 1024
                        },
                        {
                            "width": 400,
                            "height": 400
                        },
                        {
                            "width": 200,
                            "height": 200
                        },
                        {
                            "width": 100,
                            "height": 100
                        }
                    ]
                }
            ]
        }
    ],
    "items": [
        {
            "id": "https://tu-delft-heritage.github.io/beeldbank-data/manifests/f997cead-eab1-48d4-b99e-eb5cd2015ab0/canvas/0",
            "type": "Canvas",
            "height": 2480,
            "width": 2480,
            "thumbnail": [
                {
                    "id": "https://dlc.services/thumbs/v3/7/15/14d595b6-0f4c-48f7-b381-d7912efe2815/full/max/0/default.jpg",
                    "type": "Image",
                    "format": "image/jpeg",
                    "service": [
                        {
                            "@context": "http://iiif.io/api/image/3/context.json",
                            "id": "https://dlc.services/thumbs/v3/7/15/14d595b6-0f4c-48f7-b381-d7912efe2815",
                            "type": "ImageService3",
                            "profile": "level0",
                            "sizes": [
                                {
                                    "width": 1024,
                                    "height": 1024
                                },
                                {
                                    "width": 400,
                                    "height": 400
                                },
                                {
                                    "width": 200,
                                    "height": 200
                                },
                                {
                                    "width": 100,
                                    "height": 100
                                }
                            ]
                        }
                    ]
                }
            ],
            "items": [
                {
                    "id": "https://tu-delft-heritage.github.io/beeldbank-data/manifests/f997cead-eab1-48d4-b99e-eb5cd2015ab0/canvas/0/annotation-page",
                    "type": "AnnotationPage",
                    "items": [
                        {
                            "id": "https://dlc.services/iiif-img/v3/7/15/14d595b6-0f4c-48f7-b381-d7912efe2815",
                            "type": "Annotation",
                            "motivation": "painting",
                            "target": "https://tu-delft-heritage.github.io/beeldbank-data/manifests/f997cead-eab1-48d4-b99e-eb5cd2015ab0/canvas/0",
                            "body": {
                                "id": "https://dlc.services/iiif-img/v3/7/15/14d595b6-0f4c-48f7-b381-d7912efe2815/full/max/0/default.jpg",
                                "type": "Image",
                                "format": "image/jpeg",
                                "height": 2480,
                                "width": 2480,
                                "service": [
                                    {
                                        "@context": "http://iiif.io/api/image/3/context.json",
                                        "id": "https://dlc.services/iiif-img/v3/7/15/14d595b6-0f4c-48f7-b381-d7912efe2815",
                                        "type": "ImageService3",
                                        "profile": "level2"
                                    }
                                ]
                            }
                        }
                    ]
                }
            ]
        },
        {
            "id": "https://tu-delft-heritage.github.io/beeldbank-data/manifests/f997cead-eab1-48d4-b99e-eb5cd2015ab0/canvas/1",
            "type": "Canvas",
            "height": 2480,
            "width": 2480,
            "thumbnail": [
                {
                    "id": "https://dlc.services/thumbs/v3/7/15/9ef64af0-9e4f-4095-a853-9ad217694954/full/max/0/default.jpg",
                    "type": "Image",
                    "format": "image/jpeg",
                    "service": [
                        {
                            "@context": "http://iiif.io/api/image/3/context.json",
                            "id": "https://dlc.services/thumbs/v3/7/15/9ef64af0-9e4f-4095-a853-9ad217694954",
                            "type": "ImageService3",
                            "profile": "level0",
                            "sizes": [
                                {
                                    "width": 1024,
                                    "height": 1024
                                },
                                {
                                    "width": 400,
                                    "height": 400
                                },
                                {
                                    "width": 200,
                                    "height": 200
                                },
                                {
                                    "width": 100,
                                    "height": 100
                                }
                            ]
                        }
                    ]
                }
            ],
            "items": [
                {
                    "id": "https://tu-delft-heritage.github.io/beeldbank-data/manifests/f997cead-eab1-48d4-b99e-eb5cd2015ab0/canvas/1/annotation-page",
                    "type": "AnnotationPage",
                    "items": [
                        {
                            "id": "https://dlc.services/iiif-img/v3/7/15/9ef64af0-9e4f-4095-a853-9ad217694954",
                            "type": "Annotation",
                            "motivation": "painting",
                            "target": "https://tu-delft-heritage.github.io/beeldbank-data/manifests/f997cead-eab1-48d4-b99e-eb5cd2015ab0/canvas/1",
                            "body": {
                                "id": "https://dlc.services/iiif-img/v3/7/15/9ef64af0-9e4f-4095-a853-9ad217694954/full/max/0/default.jpg",
                                "type": "Image",
                                "format": "image/jpeg",
                                "height": 2480,
                                "width": 2480,
                                "service": [
                                    {
                                        "@context": "http://iiif.io/api/image/3/context.json",
                                        "id": "https://dlc.services/iiif-img/v3/7/15/9ef64af0-9e4f-4095-a853-9ad217694954",
                                        "type": "ImageService3",
                                        "profile": "level2"
                                    }
                                ]
                            }
                        }
                    ]
                }
            ]
        },
        {
            "id": "https://tu-delft-heritage.github.io/beeldbank-data/manifests/f997cead-eab1-48d4-b99e-eb5cd2015ab0/canvas/2",
            "type": "Canvas",
            "height": 2480,
            "width": 2480,
            "thumbnail": [
                {
                    "id": "https://dlc.services/thumbs/v3/7/15/83e29554-7135-48db-8729-a5096884cc7d/full/max/0/default.jpg",
                    "type": "Image",
                    "format": "image/jpeg",
                    "service": [
                        {
                            "@context": "http://iiif.io/api/image/3/context.json",
                            "id": "https://dlc.services/thumbs/v3/7/15/83e29554-7135-48db-8729-a5096884cc7d",
                            "type": "ImageService3",
                            "profile": "level0",
                            "sizes": [
                                {
                                    "width": 1024,
                                    "height": 1024
                                },
                                {
                                    "width": 400,
                                    "height": 400
                                },
                                {
                                    "width": 200,
                                    "height": 200
                                },
                                {
                                    "width": 100,
                                    "height": 100
                                }
                            ]
                        }
                    ]
                }
            ],
            "items": [
                {
                    "id": "https://tu-delft-heritage.github.io/beeldbank-data/manifests/f997cead-eab1-48d4-b99e-eb5cd2015ab0/canvas/2/annotation-page",
                    "type": "AnnotationPage",
                    "items": [
                        {
                            "id": "https://dlc.services/iiif-img/v3/7/15/83e29554-7135-48db-8729-a5096884cc7d",
                            "type": "Annotation",
                            "motivation": "painting",
                            "target": "https://tu-delft-heritage.github.io/beeldbank-data/manifests/f997cead-eab1-48d4-b99e-eb5cd2015ab0/canvas/2",
                            "body": {
                                "id": "https://dlc.services/iiif-img/v3/7/15/83e29554-7135-48db-8729-a5096884cc7d/full/max/0/default.jpg",
                                "type": "Image",
                                "format": "image/jpeg",
                                "height": 2480,
                                "width": 2480,
                                "service": [
                                    {
                                        "@context": "http://iiif.io/api/image/3/context.json",
                                        "id": "https://dlc.services/iiif-img/v3/7/15/83e29554-7135-48db-8729-a5096884cc7d",
                                        "type": "ImageService3",
                                        "profile": "level2"
                                    }
                                ]
                            }
                        }
                    ]
                }
            ]
        },
        {
            "id": "https://tu-delft-heritage.github.io/beeldbank-data/manifests/f997cead-eab1-48d4-b99e-eb5cd2015ab0/canvas/3",
            "type": "Canvas",
            "height": 2480,
            "width": 2480,
            "thumbnail": [
                {
                    "id": "https://dlc.services/thumbs/v3/7/15/31235006-46fc-45f6-9906-1131c5a35cea/full/max/0/default.jpg",
                    "type": "Image",
                    "format": "image/jpeg",
                    "service": [
                        {
                            "@context": "http://iiif.io/api/image/3/context.json",
                            "id": "https://dlc.services/thumbs/v3/7/15/31235006-46fc-45f6-9906-1131c5a35cea",
                            "type": "ImageService3",
                            "profile": "level0",
                            "sizes": [
                                {
                                    "width": 1024,
                                    "height": 1024
                                },
                                {
                                    "width": 400,
                                    "height": 400
                                },
                                {
                                    "width": 200,
                                    "height": 200
                                },
                                {
                                    "width": 100,
                                    "height": 100
                                }
                            ]
                        }
                    ]
                }
            ],
            "items": [
                {
                    "id": "https://tu-delft-heritage.github.io/beeldbank-data/manifests/f997cead-eab1-48d4-b99e-eb5cd2015ab0/canvas/3/annotation-page",
                    "type": "AnnotationPage",
                    "items": [
                        {
                            "id": "https://dlc.services/iiif-img/v3/7/15/31235006-46fc-45f6-9906-1131c5a35cea",
                            "type": "Annotation",
                            "motivation": "painting",
                            "target": "https://tu-delft-heritage.github.io/beeldbank-data/manifests/f997cead-eab1-48d4-b99e-eb5cd2015ab0/canvas/3",
                            "body": {
                                "id": "https://dlc.services/iiif-img/v3/7/15/31235006-46fc-45f6-9906-1131c5a35cea/full/max/0/default.jpg",
                                "type": "Image",
                                "format": "image/jpeg",
                                "height": 2480,
                                "width": 2480,
                                "service": [
                                    {
                                        "@context": "http://iiif.io/api/image/3/context.json",
                                        "id": "https://dlc.services/iiif-img/v3/7/15/31235006-46fc-45f6-9906-1131c5a35cea",
                                        "type": "ImageService3",
                                        "profile": "level2"
                                    }
                                ]
                            }
                        }
                    ]
                }
            ]
        },
        {
            "id": "https://tu-delft-heritage.github.io/beeldbank-data/manifests/f997cead-eab1-48d4-b99e-eb5cd2015ab0/canvas/4",
            "type": "Canvas",
            "height": 2480,
            "width": 2480,
            "thumbnail": [
                {
                    "id": "https://dlc.services/thumbs/v3/7/15/d109a276-c328-4b4f-8d16-bdbd9674e357/full/max/0/default.jpg",
                    "type": "Image",
                    "format": "image/jpeg",
                    "service": [
                        {
                            "@context": "http://iiif.io/api/image/3/context.json",
                            "id": "https://dlc.services/thumbs/v3/7/15/d109a276-c328-4b4f-8d16-bdbd9674e357",
                            "type": "ImageService3",
                            "profile": "level0",
                            "sizes": [
                                {
                                    "width": 1024,
                                    "height": 1024
                                },
                                {
                                    "width": 400,
                                    "height": 400
                                },
                                {
                                    "width": 200,
                                    "height": 200
                                },
                                {
                                    "width": 100,
                                    "height": 100
                                }
                            ]
                        }
                    ]
                }
            ],
            "items": [
                {
                    "id": "https://tu-delft-heritage.github.io/beeldbank-data/manifests/f997cead-eab1-48d4-b99e-eb5cd2015ab0/canvas/4/annotation-page",
                    "type": "AnnotationPage",
                    "items": [
                        {
                            "id": "https://dlc.services/iiif-img/v3/7/15/d109a276-c328-4b4f-8d16-bdbd9674e357",
                            "type": "Annotation",
                            "motivation": "painting",
                            "target": "https://tu-delft-heritage.github.io/beeldbank-data/manifests/f997cead-eab1-48d4-b99e-eb5cd2015ab0/canvas/4",
                            "body": {
                                "id": "https://dlc.services/iiif-img/v3/7/15/d109a276-c328-4b4f-8d16-bdbd9674e357/full/max/0/default.jpg",
                                "type": "Image",
                                "format": "image/jpeg",
                                "height": 2480,
                                "width": 2480,
                                "service": [
                                    {
                                        "@context": "http://iiif.io/api/image/3/context.json",
                                        "id": "https://dlc.services/iiif-img/v3/7/15/d109a276-c328-4b4f-8d16-bdbd9674e357",
                                        "type": "ImageService3",
                                        "profile": "level2"
                                    }
                                ]
                            }
                        }
                    ]
                }
            ]
        },
        {
            "id": "https://tu-delft-heritage.github.io/beeldbank-data/manifests/f997cead-eab1-48d4-b99e-eb5cd2015ab0/canvas/5",
            "type": "Canvas",
            "height": 2480,
            "width": 2480,
            "thumbnail": [
                {
                    "id": "https://dlc.services/thumbs/v3/7/15/89a268ca-079d-46ff-8b62-51953aeb0a2a/full/max/0/default.jpg",
                    "type": "Image",
                    "format": "image/jpeg",
                    "service": [
                        {
                            "@context": "http://iiif.io/api/image/3/context.json",
                            "id": "https://dlc.services/thumbs/v3/7/15/89a268ca-079d-46ff-8b62-51953aeb0a2a",
                            "type": "ImageService3",
                            "profile": "level0",
                            "sizes": [
                                {
                                    "width": 1024,
                                    "height": 1024
                                },
                                {
                                    "width": 400,
                                    "height": 400
                                },
                                {
                                    "width": 200,
                                    "height": 200
                                },
                                {
                                    "width": 100,
                                    "height": 100
                                }
                            ]
                        }
                    ]
                }
            ],
            "items": [
                {
                    "id": "https://tu-delft-heritage.github.io/beeldbank-data/manifests/f997cead-eab1-48d4-b99e-eb5cd2015ab0/canvas/5/annotation-page",
                    "type": "AnnotationPage",
                    "items": [
                        {
                            "id": "https://dlc.services/iiif-img/v3/7/15/89a268ca-079d-46ff-8b62-51953aeb0a2a",
                            "type": "Annotation",
                            "motivation": "painting",
                            "target": "https://tu-delft-heritage.github.io/beeldbank-data/manifests/f997cead-eab1-48d4-b99e-eb5cd2015ab0/canvas/5",
                            "body": {
                                "id": "https://dlc.services/iiif-img/v3/7/15/89a268ca-079d-46ff-8b62-51953aeb0a2a/full/max/0/default.jpg",
                                "type": "Image",
                                "format": "image/jpeg",
                                "height": 2480,
                                "width": 2480,
                                "service": [
                                    {
                                        "@context": "http://iiif.io/api/image/3/context.json",
                                        "id": "https://dlc.services/iiif-img/v3/7/15/89a268ca-079d-46ff-8b62-51953aeb0a2a",
                                        "type": "ImageService3",
                                        "profile": "level2"
                                    }
                                ]
                            }
                        }
                    ]
                }
            ]
        },
        {
            "id": "https://tu-delft-heritage.github.io/beeldbank-data/manifests/f997cead-eab1-48d4-b99e-eb5cd2015ab0/canvas/6",
            "type": "Canvas",
            "height": 2480,
            "width": 2480,
            "thumbnail": [
                {
                    "id": "https://dlc.services/thumbs/v3/7/15/501e295c-f846-42f6-950c-89337e251b03/full/max/0/default.jpg",
                    "type": "Image",
                    "format": "image/jpeg",
                    "service": [
                        {
                            "@context": "http://iiif.io/api/image/3/context.json",
                            "id": "https://dlc.services/thumbs/v3/7/15/501e295c-f846-42f6-950c-89337e251b03",
                            "type": "ImageService3",
                            "profile": "level0",
                            "sizes": [
                                {
                                    "width": 1024,
                                    "height": 1024
                                },
                                {
                                    "width": 400,
                                    "height": 400
                                },
                                {
                                    "width": 200,
                                    "height": 200
                                },
                                {
                                    "width": 100,
                                    "height": 100
                                }
                            ]
                        }
                    ]
                }
            ],
            "items": [
                {
                    "id": "https://tu-delft-heritage.github.io/beeldbank-data/manifests/f997cead-eab1-48d4-b99e-eb5cd2015ab0/canvas/6/annotation-page",
                    "type": "AnnotationPage",
                    "items": [
                        {
                            "id": "https://dlc.services/iiif-img/v3/7/15/501e295c-f846-42f6-950c-89337e251b03",
                            "type": "Annotation",
                            "motivation": "painting",
                            "target": "https://tu-delft-heritage.github.io/beeldbank-data/manifests/f997cead-eab1-48d4-b99e-eb5cd2015ab0/canvas/6",
                            "body": {
                                "id": "https://dlc.services/iiif-img/v3/7/15/501e295c-f846-42f6-950c-89337e251b03/full/max/0/default.jpg",
                                "type": "Image",
                                "format": "image/jpeg",
                                "height": 2480,
                                "width": 2480,
                                "service": [
                                    {
                                        "@context": "http://iiif.io/api/image/3/context.json",
                                        "id": "https://dlc.services/iiif-img/v3/7/15/501e295c-f846-42f6-950c-89337e251b03",
                                        "type": "ImageService3",
                                        "profile": "level2"
                                    }
                                ]
                            }
                        }
                    ]
                }
            ]
        },
        {
            "id": "https://tu-delft-heritage.github.io/beeldbank-data/manifests/f997cead-eab1-48d4-b99e-eb5cd2015ab0/canvas/7",
            "type": "Canvas",
            "height": 2480,
            "width": 2480,
            "thumbnail": [
                {
                    "id": "https://dlc.services/thumbs/v3/7/15/1066a440-fe27-4701-ae02-ecc742e8fbd3/full/max/0/default.jpg",
                    "type": "Image",
                    "format": "image/jpeg",
                    "service": [
                        {
                            "@context": "http://iiif.io/api/image/3/context.json",
                            "id": "https://dlc.services/thumbs/v3/7/15/1066a440-fe27-4701-ae02-ecc742e8fbd3",
                            "type": "ImageService3",
                            "profile": "level0",
                            "sizes": [
                                {
                                    "width": 1024,
                                    "height": 1024
                                },
                                {
                                    "width": 400,
                                    "height": 400
                                },
                                {
                                    "width": 200,
                                    "height": 200
                                },
                                {
                                    "width": 100,
                                    "height": 100
                                }
                            ]
                        }
                    ]
                }
            ],
            "items": [
                {
                    "id": "https://tu-delft-heritage.github.io/beeldbank-data/manifests/f997cead-eab1-48d4-b99e-eb5cd2015ab0/canvas/7/annotation-page",
                    "type": "AnnotationPage",
                    "items": [
                        {
                            "id": "https://dlc.services/iiif-img/v3/7/15/1066a440-fe27-4701-ae02-ecc742e8fbd3",
                            "type": "Annotation",
                            "motivation": "painting",
                            "target": "https://tu-delft-heritage.github.io/beeldbank-data/manifests/f997cead-eab1-48d4-b99e-eb5cd2015ab0/canvas/7",
                            "body": {
                                "id": "https://dlc.services/iiif-img/v3/7/15/1066a440-fe27-4701-ae02-ecc742e8fbd3/full/max/0/default.jpg",
                                "type": "Image",
                                "format": "image/jpeg",
                                "height": 2480,
                                "width": 2480,
                                "service": [
                                    {
                                        "@context": "http://iiif.io/api/image/3/context.json",
                                        "id": "https://dlc.services/iiif-img/v3/7/15/1066a440-fe27-4701-ae02-ecc742e8fbd3",
                                        "type": "ImageService3",
                                        "profile": "level2"
                                    }
                                ]
                            }
                        }
                    ]
                }
            ]
        },
        {
            "id": "https://tu-delft-heritage.github.io/beeldbank-data/manifests/f997cead-eab1-48d4-b99e-eb5cd2015ab0/canvas/8",
            "type": "Canvas",
            "height": 2480,
            "width": 2480,
            "thumbnail": [
                {
                    "id": "https://dlc.services/thumbs/v3/7/15/4681f953-216c-4b3b-bb31-5ba4e8c1be69/full/max/0/default.jpg",
                    "type": "Image",
                    "format": "image/jpeg",
                    "service": [
                        {
                            "@context": "http://iiif.io/api/image/3/context.json",
                            "id": "https://dlc.services/thumbs/v3/7/15/4681f953-216c-4b3b-bb31-5ba4e8c1be69",
                            "type": "ImageService3",
                            "profile": "level0",
                            "sizes": [
                                {
                                    "width": 1024,
                                    "height": 1024
                                },
                                {
                                    "width": 400,
                                    "height": 400
                                },
                                {
                                    "width": 200,
                                    "height": 200
                                },
                                {
                                    "width": 100,
                                    "height": 100
                                }
                            ]
                        }
                    ]
                }
            ],
            "items": [
                {
                    "id": "https://tu-delft-heritage.github.io/beeldbank-data/manifests/f997cead-eab1-48d4-b99e-eb5cd2015ab0/canvas/8/annotation-page",
                    "type": "AnnotationPage",
                    "items": [
                        {
                            "id": "https://dlc.services/iiif-img/v3/7/15/4681f953-216c-4b3b-bb31-5ba4e8c1be69",
                            "type": "Annotation",
                            "motivation": "painting",
                            "target": "https://tu-delft-heritage.github.io/beeldbank-data/manifests/f997cead-eab1-48d4-b99e-eb5cd2015ab0/canvas/8",
                            "body": {
                                "id": "https://dlc.services/iiif-img/v3/7/15/4681f953-216c-4b3b-bb31-5ba4e8c1be69/full/max/0/default.jpg",
                                "type": "Image",
                                "format": "image/jpeg",
                                "height": 2480,
                                "width": 2480,
                                "service": [
                                    {
                                        "@context": "http://iiif.io/api/image/3/context.json",
                                        "id": "https://dlc.services/iiif-img/v3/7/15/4681f953-216c-4b3b-bb31-5ba4e8c1be69",
                                        "type": "ImageService3",
                                        "profile": "level2"
                                    }
                                ]
                            }
                        }
                    ]
                }
            ]
        }
    ]
}