{
        "@context": "http://iiif.io/api/presentation/2/context.json",
        "@id": "https://dlc.services/iiif-resource/7/string1string2string3/kalktekeningen/AA271067",
        "@type": "sc:Manifest",
        "metadata": [
                {
                        "label": "Titel",
                        "value": "Windtunnel uitbreiding"
                },
                {
                        "label": "Koker",
                        "value": "AA271067"
                },
                {
                        "label": "Gebouw",
                        "value": "Lage Snelheden Laboratorium"
                }
        ],
        "sequences": [
                {
                        "@id": "https://dlc.services/iiif-query/7/?sequence=n1&manifest=s1&canvas=n2&s1=kalktekeningen&n1=",
                        "@type": "sc:Sequence",
                        "label": "Sequence 0",
                        "canvases": [
                                {
                                        "@id": "https://dlc.services/iiif-query/7/?canvas=n2&manifest=s1&sequence=n1&s1=kalktekeningen&n1=&n2=5025",
                                        "@type": "sc:Canvas",
                                        "thumbnail": {
                                                "@id": "https://dlc.services/thumbs/7/14/70d4a932-850d-4d93-80f4-a365a5a6dd15/full/full/0/default.jpg",
                                                "@type": "dctypes:Image",
                                                "service": {
                                                        "@context": "http://iiif.io/api/image/2/context.json",
                                                        "@id": "https://apex.dlc.services/thumbs/7/14/70d4a932-850d-4d93-80f4-a365a5a6dd15",
                                                        "profile": [
                                                                "http://iiif.io/api/image/2/level0.json",
                                                                {
                                                                        "formats": [
                                                                                "jpg"
                                                                        ],
                                                                        "qualities": [
                                                                                "color"
                                                                        ],
                                                                        "supports": [
                                                                                "sizeByWhListed"
                                                                        ]
                                                                }
                                                        ],
                                                        "width": 1024,
                                                        "height": 634,
                                                        "sizes": [
                                                                {
                                                                        "width": 1024,
                                                                        "height": 634
                                                                },
                                                                {
                                                                        "width": 400,
                                                                        "height": 248
                                                                },
                                                                {
                                                                        "width": 200,
                                                                        "height": 124
                                                                },
                                                                {
                                                                        "width": 100,
                                                                        "height": 62
                                                                }
                                                        ]
                                                }
                                        },
                                        "height": 6340,
                                        "width": 10242,
                                        "images": [
                                                {
                                                        "@id": "https://dlc.services/iiif-img/7/14/70d4a932-850d-4d93-80f4-a365a5a6dd15/anno",
                                                        "@type": "oa:Annotation",
                                                        "motivation": "sc:painting",
                                                        "resource": {
                                                                "@id": "https://dlc.services/iiif-img/7/14/70d4a932-850d-4d93-80f4-a365a5a6dd15/full/!2000,2000/0/default.jpg",
                                                                "@type": "dctypes:Image",
                                                                "height": 6340,
                                                                "width": 10242,
                                                                "service": {
                                                                        "@id": "https://dlc.services/iiif-img/7/14/70d4a932-850d-4d93-80f4-a365a5a6dd15",
                                                                        "protocol": "http://iiif.io/api/image",
                                                                        "height": 6340,
                                                                        "width": 10242,
                                                                        "profile": "http://iiif.io/api/image/2/level1.json"
                                                                }
                                                        },
                                                        "on": "https://dlc.services/iiif-query/7/?canvas=n2&manifest=s1&sequence=n1&s1=kalktekeningen&n1=&n2=5025"
                                                }
                                        ],
                                        "label": "Geen omschrijving"
                                },
                                {
                                        "@id": "https://dlc.services/iiif-query/7/?canvas=n2&manifest=s1&sequence=n1&s1=kalktekeningen&n1=&n2=5026",
                                        "@type": "sc:Canvas",
                                        "thumbnail": {
                                                "@id": "https://dlc.services/thumbs/7/14/34fd559c-a65c-42cd-8a0b-aab996a4e277/full/full/0/default.jpg",
                                                "@type": "dctypes:Image",
                                                "service": {
                                                        "@context": "http://iiif.io/api/image/2/context.json",
                                                        "@id": "https://apex.dlc.services/thumbs/7/14/34fd559c-a65c-42cd-8a0b-aab996a4e277",
                                                        "profile": [
                                                                "http://iiif.io/api/image/2/level0.json",
                                                                {
                                                                        "formats": [
                                                                                "jpg"
                                                                        ],
                                                                        "qualities": [
                                                                                "color"
                                                                        ],
                                                                        "supports": [
                                                                                "sizeByWhListed"
                                                                        ]
                                                                }
                                                        ],
                                                        "width": 1024,
                                                        "height": 526,
                                                        "sizes": [
                                                                {
                                                                        "width": 1024,
                                                                        "height": 526
                                                                },
                                                                {
                                                                        "width": 400,
                                                                        "height": 206
                                                                },
                                                                {
                                                                        "width": 200,
                                                                        "height": 103
                                                                },
                                                                {
                                                                        "width": 100,
                                                                        "height": 51
                                                                }
                                                        ]
                                                }
                                        },
                                        "height": 9264,
                                        "width": 18026,
                                        "images": [
                                                {
                                                        "@id": "https://dlc.services/iiif-img/7/14/34fd559c-a65c-42cd-8a0b-aab996a4e277/anno",
                                                        "@type": "oa:Annotation",
                                                        "motivation": "sc:painting",
                                                        "resource": {
                                                                "@id": "https://dlc.services/iiif-img/7/14/34fd559c-a65c-42cd-8a0b-aab996a4e277/full/!2000,2000/0/default.jpg",
                                                                "@type": "dctypes:Image",
                                                                "height": 9264,
                                                                "width": 18026,
                                                                "service": {
                                                                        "@id": "https://dlc.services/iiif-img/7/14/34fd559c-a65c-42cd-8a0b-aab996a4e277",
                                                                        "protocol": "http://iiif.io/api/image",
                                                                        "height": 9264,
                                                                        "width": 18026,
                                                                        "profile": "http://iiif.io/api/image/2/level1.json"
                                                                }
                                                        },
                                                        "on": "https://dlc.services/iiif-query/7/?canvas=n2&manifest=s1&sequence=n1&s1=kalktekeningen&n1=&n2=5026"
                                                }
                                        ],
                                        "label": "Zuidgevel"
                                },
                                {
                                        "@id": "https://dlc.services/iiif-query/7/?canvas=n2&manifest=s1&sequence=n1&s1=kalktekeningen&n1=&n2=5027",
                                        "@type": "sc:Canvas",
                                        "thumbnail": {
                                                "@id": "https://dlc.services/thumbs/7/14/fa3f64e0-a62d-4c47-83c6-7ec5c3edde6f/full/full/0/default.jpg",
                                                "@type": "dctypes:Image",
                                                "service": {
                                                        "@context": "http://iiif.io/api/image/2/context.json",
                                                        "@id": "https://apex.dlc.services/thumbs/7/14/fa3f64e0-a62d-4c47-83c6-7ec5c3edde6f",
                                                        "profile": [
                                                                "http://iiif.io/api/image/2/level0.json",
                                                                {
                                                                        "formats": [
                                                                                "jpg"
                                                                        ],
                                                                        "qualities": [
                                                                                "color"
                                                                        ],
                                                                        "supports": [
                                                                                "sizeByWhListed"
                                                                        ]
                                                                }
                                                        ],
                                                        "width": 1024,
                                                        "height": 540,
                                                        "sizes": [
                                                                {
                                                                        "width": 1024,
                                                                        "height": 540
                                                                },
                                                                {
                                                                        "width": 400,
                                                                        "height": 211
                                                                },
                                                                {
                                                                        "width": 200,
                                                                        "height": 105
                                                                },
                                                                {
                                                                        "width": 100,
                                                                        "height": 53
                                                                }
                                                        ]
                                                }
                                        },
                                        "height": 9054,
                                        "width": 17170,
                                        "images": [
                                                {
                                                        "@id": "https://dlc.services/iiif-img/7/14/fa3f64e0-a62d-4c47-83c6-7ec5c3edde6f/anno",
                                                        "@type": "oa:Annotation",
                                                        "motivation": "sc:painting",
                                                        "resource": {
                                                                "@id": "https://dlc.services/iiif-img/7/14/fa3f64e0-a62d-4c47-83c6-7ec5c3edde6f/full/!2000,2000/0/default.jpg",
                                                                "@type": "dctypes:Image",
                                                                "height": 9054,
                                                                "width": 17170,
                                                                "service": {
                                                                        "@id": "https://dlc.services/iiif-img/7/14/fa3f64e0-a62d-4c47-83c6-7ec5c3edde6f",
                                                                        "protocol": "http://iiif.io/api/image",
                                                                        "height": 9054,
                                                                        "width": 17170,
                                                                        "profile": "http://iiif.io/api/image/2/level1.json"
                                                                }
                                                        },
                                                        "on": "https://dlc.services/iiif-query/7/?canvas=n2&manifest=s1&sequence=n1&s1=kalktekeningen&n1=&n2=5027"
                                                }
                                        ],
                                        "label": "Westgevel"
                                },
                                {
                                        "@id": "https://dlc.services/iiif-query/7/?canvas=n2&manifest=s1&sequence=n1&s1=kalktekeningen&n1=&n2=5028",
                                        "@type": "sc:Canvas",
                                        "thumbnail": {
                                                "@id": "https://dlc.services/thumbs/7/14/0632dd85-355f-4da6-b5f9-c59e8c7cbe64/full/full/0/default.jpg",
                                                "@type": "dctypes:Image",
                                                "service": {
                                                        "@context": "http://iiif.io/api/image/2/context.json",
                                                        "@id": "https://apex.dlc.services/thumbs/7/14/0632dd85-355f-4da6-b5f9-c59e8c7cbe64",
                                                        "profile": [
                                                                "http://iiif.io/api/image/2/level0.json",
                                                                {
                                                                        "formats": [
                                                                                "jpg"
                                                                        ],
                                                                        "qualities": [
                                                                                "color"
                                                                        ],
                                                                        "supports": [
                                                                                "sizeByWhListed"
                                                                        ]
                                                                }
                                                        ],
                                                        "width": 1024,
                                                        "height": 528,
                                                        "sizes": [
                                                                {
                                                                        "width": 1024,
                                                                        "height": 528
                                                                },
                                                                {
                                                                        "width": 400,
                                                                        "height": 206
                                                                },
                                                                {
                                                                        "width": 200,
                                                                        "height": 103
                                                                },
                                                                {
                                                                        "width": 100,
                                                                        "height": 52
                                                                }
                                                        ]
                                                }
                                        },
                                        "height": 9282,
                                        "width": 18002,
                                        "images": [
                                                {
                                                        "@id": "https://dlc.services/iiif-img/7/14/0632dd85-355f-4da6-b5f9-c59e8c7cbe64/anno",
                                                        "@type": "oa:Annotation",
                                                        "motivation": "sc:painting",
                                                        "resource": {
                                                                "@id": "https://dlc.services/iiif-img/7/14/0632dd85-355f-4da6-b5f9-c59e8c7cbe64/full/!2000,2000/0/default.jpg",
                                                                "@type": "dctypes:Image",
                                                                "height": 9282,
                                                                "width": 18002,
                                                                "service": {
                                                                        "@id": "https://dlc.services/iiif-img/7/14/0632dd85-355f-4da6-b5f9-c59e8c7cbe64",
                                                                        "protocol": "http://iiif.io/api/image",
                                                                        "height": 9282,
                                                                        "width": 18002,
                                                                        "profile": "http://iiif.io/api/image/2/level1.json"
                                                                }
                                                        },
                                                        "on": "https://dlc.services/iiif-query/7/?canvas=n2&manifest=s1&sequence=n1&s1=kalktekeningen&n1=&n2=5028"
                                                }
                                        ],
                                        "label": "Noordgevel"
                                },
                                {
                                        "@id": "https://dlc.services/iiif-query/7/?canvas=n2&manifest=s1&sequence=n1&s1=kalktekeningen&n1=&n2=5029",
                                        "@type": "sc:Canvas",
                                        "thumbnail": {
                                                "@id": "https://dlc.services/thumbs/7/14/f3033140-0ef5-4c04-a473-00a9c1fecd59/full/full/0/default.jpg",
                                                "@type": "dctypes:Image",
                                                "service": {
                                                        "@context": "http://iiif.io/api/image/2/context.json",
                                                        "@id": "https://apex.dlc.services/thumbs/7/14/f3033140-0ef5-4c04-a473-00a9c1fecd59",
                                                        "profile": [
                                                                "http://iiif.io/api/image/2/level0.json",
                                                                {
                                                                        "formats": [
                                                                                "jpg"
                                                                        ],
                                                                        "qualities": [
                                                                                "color"
                                                                        ],
                                                                        "supports": [
                                                                                "sizeByWhListed"
                                                                        ]
                                                                }
                                                        ],
                                                        "width": 1024,
                                                        "height": 532,
                                                        "sizes": [
                                                                {
                                                                        "width": 1024,
                                                                        "height": 532
                                                                },
                                                                {
                                                                        "width": 400,
                                                                        "height": 208
                                                                },
                                                                {
                                                                        "width": 200,
                                                                        "height": 104
                                                                },
                                                                {
                                                                        "width": 100,
                                                                        "height": 52
                                                                }
                                                        ]
                                                }
                                        },
                                        "height": 9560,
                                        "width": 18418,
                                        "images": [
                                                {
                                                        "@id": "https://dlc.services/iiif-img/7/14/f3033140-0ef5-4c04-a473-00a9c1fecd59/anno",
                                                        "@type": "oa:Annotation",
                                                        "motivation": "sc:painting",
                                                        "resource": {
                                                                "@id": "https://dlc.services/iiif-img/7/14/f3033140-0ef5-4c04-a473-00a9c1fecd59/full/!2000,2000/0/default.jpg",
                                                                "@type": "dctypes:Image",
                                                                "height": 9560,
                                                                "width": 18418,
                                                                "service": {
                                                                        "@id": "https://dlc.services/iiif-img/7/14/f3033140-0ef5-4c04-a473-00a9c1fecd59",
                                                                        "protocol": "http://iiif.io/api/image",
                                                                        "height": 9560,
                                                                        "width": 18418,
                                                                        "profile": "http://iiif.io/api/image/2/level1.json"
                                                                }
                                                        },
                                                        "on": "https://dlc.services/iiif-query/7/?canvas=n2&manifest=s1&sequence=n1&s1=kalktekeningen&n1=&n2=5029"
                                                }
                                        ],
                                        "label": "Zuidgevel"
                                },
                                {
                                        "@id": "https://dlc.services/iiif-query/7/?canvas=n2&manifest=s1&sequence=n1&s1=kalktekeningen&n1=&n2=5030",
                                        "@type": "sc:Canvas",
                                        "thumbnail": {
                                                "@id": "https://dlc.services/thumbs/7/14/ef5256e7-a5ed-473a-a846-cad7319d68a3/full/full/0/default.jpg",
                                                "@type": "dctypes:Image",
                                                "service": {
                                                        "@context": "http://iiif.io/api/image/2/context.json",
                                                        "@id": "https://apex.dlc.services/thumbs/7/14/ef5256e7-a5ed-473a-a846-cad7319d68a3",
                                                        "profile": [
                                                                "http://iiif.io/api/image/2/level0.json",
                                                                {
                                                                        "formats": [
                                                                                "jpg"
                                                                        ],
                                                                        "qualities": [
                                                                                "color"
                                                                        ],
                                                                        "supports": [
                                                                                "sizeByWhListed"
                                                                        ]
                                                                }
                                                        ],
                                                        "width": 1024,
                                                        "height": 526,
                                                        "sizes": [
                                                                {
                                                                        "width": 1024,
                                                                        "height": 526
                                                                },
                                                                {
                                                                        "width": 400,
                                                                        "height": 205
                                                                },
                                                                {
                                                                        "width": 200,
                                                                        "height": 103
                                                                },
                                                                {
                                                                        "width": 100,
                                                                        "height": 51
                                                                }
                                                        ]
                                                }
                                        },
                                        "height": 9322,
                                        "width": 18150,
                                        "images": [
                                                {
                                                        "@id": "https://dlc.services/iiif-img/7/14/ef5256e7-a5ed-473a-a846-cad7319d68a3/anno",
                                                        "@type": "oa:Annotation",
                                                        "motivation": "sc:painting",
                                                        "resource": {
                                                                "@id": "https://dlc.services/iiif-img/7/14/ef5256e7-a5ed-473a-a846-cad7319d68a3/full/!2000,2000/0/default.jpg",
                                                                "@type": "dctypes:Image",
                                                                "height": 9322,
                                                                "width": 18150,
                                                                "service": {
                                                                        "@id": "https://dlc.services/iiif-img/7/14/ef5256e7-a5ed-473a-a846-cad7319d68a3",
                                                                        "protocol": "http://iiif.io/api/image",
                                                                        "height": 9322,
                                                                        "width": 18150,
                                                                        "profile": "http://iiif.io/api/image/2/level1.json"
                                                                }
                                                        },
                                                        "on": "https://dlc.services/iiif-query/7/?canvas=n2&manifest=s1&sequence=n1&s1=kalktekeningen&n1=&n2=5030"
                                                }
                                        ],
                                        "label": "Zuidgevel"
                                },
                                {
                                        "@id": "https://dlc.services/iiif-query/7/?canvas=n2&manifest=s1&sequence=n1&s1=kalktekeningen&n1=&n2=5031",
                                        "@type": "sc:Canvas",
                                        "thumbnail": {
                                                "@id": "https://dlc.services/thumbs/7/14/69177886-cf10-49bb-8c91-abbc076c7dc2/full/full/0/default.jpg",
                                                "@type": "dctypes:Image",
                                                "service": {
                                                        "@context": "http://iiif.io/api/image/2/context.json",
                                                        "@id": "https://apex.dlc.services/thumbs/7/14/69177886-cf10-49bb-8c91-abbc076c7dc2",
                                                        "profile": [
                                                                "http://iiif.io/api/image/2/level0.json",
                                                                {
                                                                        "formats": [
                                                                                "jpg"
                                                                        ],
                                                                        "qualities": [
                                                                                "color"
                                                                        ],
                                                                        "supports": [
                                                                                "sizeByWhListed"
                                                                        ]
                                                                }
                                                        ],
                                                        "width": 1024,
                                                        "height": 588,
                                                        "sizes": [
                                                                {
                                                                        "width": 1024,
                                                                        "height": 588
                                                                },
                                                                {
                                                                        "width": 400,
                                                                        "height": 230
                                                                },
                                                                {
                                                                        "width": 200,
                                                                        "height": 115
                                                                },
                                                                {
                                                                        "width": 100,
                                                                        "height": 57
                                                                }
                                                        ]
                                                }
                                        },
                                        "height": 9752,
                                        "width": 16978,
                                        "images": [
                                                {
                                                        "@id": "https://dlc.services/iiif-img/7/14/69177886-cf10-49bb-8c91-abbc076c7dc2/anno",
                                                        "@type": "oa:Annotation",
                                                        "motivation": "sc:painting",
                                                        "resource": {
                                                                "@id": "https://dlc.services/iiif-img/7/14/69177886-cf10-49bb-8c91-abbc076c7dc2/full/!2000,2000/0/default.jpg",
                                                                "@type": "dctypes:Image",
                                                                "height": 9752,
                                                                "width": 16978,
                                                                "service": {
                                                                        "@id": "https://dlc.services/iiif-img/7/14/69177886-cf10-49bb-8c91-abbc076c7dc2",
                                                                        "protocol": "http://iiif.io/api/image",
                                                                        "height": 9752,
                                                                        "width": 16978,
                                                                        "profile": "http://iiif.io/api/image/2/level1.json"
                                                                }
                                                        },
                                                        "on": "https://dlc.services/iiif-query/7/?canvas=n2&manifest=s1&sequence=n1&s1=kalktekeningen&n1=&n2=5031"
                                                }
                                        ],
                                        "label": "Westgevel"
                                },
                                {
                                        "@id": "https://dlc.services/iiif-query/7/?canvas=n2&manifest=s1&sequence=n1&s1=kalktekeningen&n1=&n2=5032",
                                        "@type": "sc:Canvas",
                                        "thumbnail": {
                                                "@id": "https://dlc.services/thumbs/7/14/876dd8a7-58f7-4599-8734-60974b1f1627/full/full/0/default.jpg",
                                                "@type": "dctypes:Image",
                                                "service": {
                                                        "@context": "http://iiif.io/api/image/2/context.json",
                                                        "@id": "https://apex.dlc.services/thumbs/7/14/876dd8a7-58f7-4599-8734-60974b1f1627",
                                                        "profile": [
                                                                "http://iiif.io/api/image/2/level0.json",
                                                                {
                                                                        "formats": [
                                                                                "jpg"
                                                                        ],
                                                                        "qualities": [
                                                                                "color"
                                                                        ],
                                                                        "supports": [
                                                                                "sizeByWhListed"
                                                                        ]
                                                                }
                                                        ],
                                                        "width": 1024,
                                                        "height": 524,
                                                        "sizes": [
                                                                {
                                                                        "width": 1024,
                                                                        "height": 524
                                                                },
                                                                {
                                                                        "width": 400,
                                                                        "height": 205
                                                                },
                                                                {
                                                                        "width": 200,
                                                                        "height": 102
                                                                },
                                                                {
                                                                        "width": 100,
                                                                        "height": 51
                                                                }
                                                        ]
                                                }
                                        },
                                        "height": 9446,
                                        "width": 18448,
                                        "images": [
                                                {
                                                        "@id": "https://dlc.services/iiif-img/7/14/876dd8a7-58f7-4599-8734-60974b1f1627/anno",
                                                        "@type": "oa:Annotation",
                                                        "motivation": "sc:painting",
                                                        "resource": {
                                                                "@id": "https://dlc.services/iiif-img/7/14/876dd8a7-58f7-4599-8734-60974b1f1627/full/!2000,2000/0/default.jpg",
                                                                "@type": "dctypes:Image",
                                                                "height": 9446,
                                                                "width": 18448,
                                                                "service": {
                                                                        "@id": "https://dlc.services/iiif-img/7/14/876dd8a7-58f7-4599-8734-60974b1f1627",
                                                                        "protocol": "http://iiif.io/api/image",
                                                                        "height": 9446,
                                                                        "width": 18448,
                                                                        "profile": "http://iiif.io/api/image/2/level1.json"
                                                                }
                                                        },
                                                        "on": "https://dlc.services/iiif-query/7/?canvas=n2&manifest=s1&sequence=n1&s1=kalktekeningen&n1=&n2=5032"
                                                }
                                        ],
                                        "label": "Noordgevel"
                                },
                                {
                                        "@id": "https://dlc.services/iiif-query/7/?canvas=n2&manifest=s1&sequence=n1&s1=kalktekeningen&n1=&n2=5033",
                                        "@type": "sc:Canvas",
                                        "thumbnail": {
                                                "@id": "https://dlc.services/thumbs/7/14/762f94d4-0df5-4d79-aae6-17d5cf9a022b/full/full/0/default.jpg",
                                                "@type": "dctypes:Image",
                                                "service": {
                                                        "@context": "http://iiif.io/api/image/2/context.json",
                                                        "@id": "https://apex.dlc.services/thumbs/7/14/762f94d4-0df5-4d79-aae6-17d5cf9a022b",
                                                        "profile": [
                                                                "http://iiif.io/api/image/2/level0.json",
                                                                {
                                                                        "formats": [
                                                                                "jpg"
                                                                        ],
                                                                        "qualities": [
                                                                                "color"
                                                                        ],
                                                                        "supports": [
                                                                                "sizeByWhListed"
                                                                        ]
                                                                }
                                                        ],
                                                        "width": 1024,
                                                        "height": 590,
                                                        "sizes": [
                                                                {
                                                                        "width": 1024,
                                                                        "height": 590
                                                                },
                                                                {
                                                                        "width": 400,
                                                                        "height": 231
                                                                },
                                                                {
                                                                        "width": 200,
                                                                        "height": 115
                                                                },
                                                                {
                                                                        "width": 100,
                                                                        "height": 58
                                                                }
                                                        ]
                                                }
                                        },
                                        "height": 9320,
                                        "width": 16166,
                                        "images": [
                                                {
                                                        "@id": "https://dlc.services/iiif-img/7/14/762f94d4-0df5-4d79-aae6-17d5cf9a022b/anno",
                                                        "@type": "oa:Annotation",
                                                        "motivation": "sc:painting",
                                                        "resource": {
                                                                "@id": "https://dlc.services/iiif-img/7/14/762f94d4-0df5-4d79-aae6-17d5cf9a022b/full/!2000,2000/0/default.jpg",
                                                                "@type": "dctypes:Image",
                                                                "height": 9320,
                                                                "width": 16166,
                                                                "service": {
                                                                        "@id": "https://dlc.services/iiif-img/7/14/762f94d4-0df5-4d79-aae6-17d5cf9a022b",
                                                                        "protocol": "http://iiif.io/api/image",
                                                                        "height": 9320,
                                                                        "width": 16166,
                                                                        "profile": "http://iiif.io/api/image/2/level1.json"
                                                                }
                                                        },
                                                        "on": "https://dlc.services/iiif-query/7/?canvas=n2&manifest=s1&sequence=n1&s1=kalktekeningen&n1=&n2=5033"
                                                }
                                        ],
                                        "label": "Westgevel uitbreid met doorsnede bestaand gebouw"
                                },
                                {
                                        "@id": "https://dlc.services/iiif-query/7/?canvas=n2&manifest=s1&sequence=n1&s1=kalktekeningen&n1=&n2=5034",
                                        "@type": "sc:Canvas",
                                        "thumbnail": {
                                                "@id": "https://dlc.services/thumbs/7/14/2dccd7bf-fc81-4255-a4ec-bc7515d8ab94/full/full/0/default.jpg",
                                                "@type": "dctypes:Image",
                                                "service": {
                                                        "@context": "http://iiif.io/api/image/2/context.json",
                                                        "@id": "https://apex.dlc.services/thumbs/7/14/2dccd7bf-fc81-4255-a4ec-bc7515d8ab94",
                                                        "profile": [
                                                                "http://iiif.io/api/image/2/level0.json",
                                                                {
                                                                        "formats": [
                                                                                "jpg"
                                                                        ],
                                                                        "qualities": [
                                                                                "color"
                                                                        ],
                                                                        "supports": [
                                                                                "sizeByWhListed"
                                                                        ]
                                                                }
                                                        ],
                                                        "width": 1024,
                                                        "height": 598,
                                                        "sizes": [
                                                                {
                                                                        "width": 1024,
                                                                        "height": 598
                                                                },
                                                                {
                                                                        "width": 400,
                                                                        "height": 234
                                                                },
                                                                {
                                                                        "width": 200,
                                                                        "height": 117
                                                                },
                                                                {
                                                                        "width": 100,
                                                                        "height": 58
                                                                }
                                                        ]
                                                }
                                        },
                                        "height": 9320,
                                        "width": 15958,
                                        "images": [
                                                {
                                                        "@id": "https://dlc.services/iiif-img/7/14/2dccd7bf-fc81-4255-a4ec-bc7515d8ab94/anno",
                                                        "@type": "oa:Annotation",
                                                        "motivation": "sc:painting",
                                                        "resource": {
                                                                "@id": "https://dlc.services/iiif-img/7/14/2dccd7bf-fc81-4255-a4ec-bc7515d8ab94/full/!2000,2000/0/default.jpg",
                                                                "@type": "dctypes:Image",
                                                                "height": 9320,
                                                                "width": 15958,
                                                                "service": {
                                                                        "@id": "https://dlc.services/iiif-img/7/14/2dccd7bf-fc81-4255-a4ec-bc7515d8ab94",
                                                                        "protocol": "http://iiif.io/api/image",
                                                                        "height": 9320,
                                                                        "width": 15958,
                                                                        "profile": "http://iiif.io/api/image/2/level1.json"
                                                                }
                                                        },
                                                        "on": "https://dlc.services/iiif-query/7/?canvas=n2&manifest=s1&sequence=n1&s1=kalktekeningen&n1=&n2=5034"
                                                }
                                        ],
                                        "label": "Westgevel uitbreid met doorsnede bestaand gebouw"
                                },
                                {
                                        "@id": "https://dlc.services/iiif-query/7/?canvas=n2&manifest=s1&sequence=n1&s1=kalktekeningen&n1=&n2=5035",
                                        "@type": "sc:Canvas",
                                        "thumbnail": {
                                                "@id": "https://dlc.services/thumbs/7/14/70777f57-015e-4611-a60a-d0778f399c79/full/full/0/default.jpg",
                                                "@type": "dctypes:Image",
                                                "service": {
                                                        "@context": "http://iiif.io/api/image/2/context.json",
                                                        "@id": "https://apex.dlc.services/thumbs/7/14/70777f57-015e-4611-a60a-d0778f399c79",
                                                        "profile": [
                                                                "http://iiif.io/api/image/2/level0.json",
                                                                {
                                                                        "formats": [
                                                                                "jpg"
                                                                        ],
                                                                        "qualities": [
                                                                                "color"
                                                                        ],
                                                                        "supports": [
                                                                                "sizeByWhListed"
                                                                        ]
                                                                }
                                                        ],
                                                        "width": 1024,
                                                        "height": 610,
                                                        "sizes": [
                                                                {
                                                                        "width": 1024,
                                                                        "height": 610
                                                                },
                                                                {
                                                                        "width": 400,
                                                                        "height": 238
                                                                },
                                                                {
                                                                        "width": 200,
                                                                        "height": 119
                                                                },
                                                                {
                                                                        "width": 100,
                                                                        "height": 60
                                                                }
                                                        ]
                                                }
                                        },
                                        "height": 9676,
                                        "width": 16252,
                                        "images": [
                                                {
                                                        "@id": "https://dlc.services/iiif-img/7/14/70777f57-015e-4611-a60a-d0778f399c79/anno",
                                                        "@type": "oa:Annotation",
                                                        "motivation": "sc:painting",
                                                        "resource": {
                                                                "@id": "https://dlc.services/iiif-img/7/14/70777f57-015e-4611-a60a-d0778f399c79/full/!2000,2000/0/default.jpg",
                                                                "@type": "dctypes:Image",
                                                                "height": 9676,
                                                                "width": 16252,
                                                                "service": {
                                                                        "@id": "https://dlc.services/iiif-img/7/14/70777f57-015e-4611-a60a-d0778f399c79",
                                                                        "protocol": "http://iiif.io/api/image",
                                                                        "height": 9676,
                                                                        "width": 16252,
                                                                        "profile": "http://iiif.io/api/image/2/level1.json"
                                                                }
                                                        },
                                                        "on": "https://dlc.services/iiif-query/7/?canvas=n2&manifest=s1&sequence=n1&s1=kalktekeningen&n1=&n2=5035"
                                                }
                                        ],
                                        "label": "Westgevel uitbreid met doorsnede bestaand gebouw"
                                },
                                {
                                        "@id": "https://dlc.services/iiif-query/7/?canvas=n2&manifest=s1&sequence=n1&s1=kalktekeningen&n1=&n2=5036",
                                        "@type": "sc:Canvas",
                                        "thumbnail": {
                                                "@id": "https://dlc.services/thumbs/7/14/9fb089b9-ff74-4691-972a-5815f1f437ee/full/full/0/default.jpg",
                                                "@type": "dctypes:Image",
                                                "service": {
                                                        "@context": "http://iiif.io/api/image/2/context.json",
                                                        "@id": "https://apex.dlc.services/thumbs/7/14/9fb089b9-ff74-4691-972a-5815f1f437ee",
                                                        "profile": [
                                                                "http://iiif.io/api/image/2/level0.json",
                                                                {
                                                                        "formats": [
                                                                                "jpg"
                                                                        ],
                                                                        "qualities": [
                                                                                "color"
                                                                        ],
                                                                        "supports": [
                                                                                "sizeByWhListed"
                                                                        ]
                                                                }
                                                        ],
                                                        "width": 1024,
                                                        "height": 645,
                                                        "sizes": [
                                                                {
                                                                        "width": 1024,
                                                                        "height": 645
                                                                },
                                                                {
                                                                        "width": 400,
                                                                        "height": 252
                                                                },
                                                                {
                                                                        "width": 200,
                                                                        "height": 126
                                                                },
                                                                {
                                                                        "width": 100,
                                                                        "height": 63
                                                                }
                                                        ]
                                                }
                                        },
                                        "height": 11324,
                                        "width": 17984,
                                        "images": [
                                                {
                                                        "@id": "https://dlc.services/iiif-img/7/14/9fb089b9-ff74-4691-972a-5815f1f437ee/anno",
                                                        "@type": "oa:Annotation",
                                                        "motivation": "sc:painting",
                                                        "resource": {
                                                                "@id": "https://dlc.services/iiif-img/7/14/9fb089b9-ff74-4691-972a-5815f1f437ee/full/!2000,2000/0/default.jpg",
                                                                "@type": "dctypes:Image",
                                                                "height": 11324,
                                                                "width": 17984,
                                                                "service": {
                                                                        "@id": "https://dlc.services/iiif-img/7/14/9fb089b9-ff74-4691-972a-5815f1f437ee",
                                                                        "protocol": "http://iiif.io/api/image",
                                                                        "height": 11324,
                                                                        "width": 17984,
                                                                        "profile": "http://iiif.io/api/image/2/level1.json"
                                                                }
                                                        },
                                                        "on": "https://dlc.services/iiif-query/7/?canvas=n2&manifest=s1&sequence=n1&s1=kalktekeningen&n1=&n2=5036"
                                                }
                                        ],
                                        "label": "Principe-details buitenkozijnen, borstweringen en dakranden"
                                },
                                {
                                        "@id": "https://dlc.services/iiif-query/7/?canvas=n2&manifest=s1&sequence=n1&s1=kalktekeningen&n1=&n2=5037",
                                        "@type": "sc:Canvas",
                                        "thumbnail": {
                                                "@id": "https://dlc.services/thumbs/7/14/e06e3f8f-4827-4e48-810f-906bb9eaf8ff/full/full/0/default.jpg",
                                                "@type": "dctypes:Image",
                                                "service": {
                                                        "@context": "http://iiif.io/api/image/2/context.json",
                                                        "@id": "https://apex.dlc.services/thumbs/7/14/e06e3f8f-4827-4e48-810f-906bb9eaf8ff",
                                                        "profile": [
                                                                "http://iiif.io/api/image/2/level0.json",
                                                                {
                                                                        "formats": [
                                                                                "jpg"
                                                                        ],
                                                                        "qualities": [
                                                                                "color"
                                                                        ],
                                                                        "supports": [
                                                                                "sizeByWhListed"
                                                                        ]
                                                                }
                                                        ],
                                                        "width": 1024,
                                                        "height": 681,
                                                        "sizes": [
                                                                {
                                                                        "width": 1024,
                                                                        "height": 681
                                                                },
                                                                {
                                                                        "width": 400,
                                                                        "height": 266
                                                                },
                                                                {
                                                                        "width": 200,
                                                                        "height": 133
                                                                },
                                                                {
                                                                        "width": 100,
                                                                        "height": 67
                                                                }
                                                        ]
                                                }
                                        },
                                        "height": 12054,
                                        "width": 18118,
                                        "images": [
                                                {
                                                        "@id": "https://dlc.services/iiif-img/7/14/e06e3f8f-4827-4e48-810f-906bb9eaf8ff/anno",
                                                        "@type": "oa:Annotation",
                                                        "motivation": "sc:painting",
                                                        "resource": {
                                                                "@id": "https://dlc.services/iiif-img/7/14/e06e3f8f-4827-4e48-810f-906bb9eaf8ff/full/!2000,2000/0/default.jpg",
                                                                "@type": "dctypes:Image",
                                                                "height": 12054,
                                                                "width": 18118,
                                                                "service": {
                                                                        "@id": "https://dlc.services/iiif-img/7/14/e06e3f8f-4827-4e48-810f-906bb9eaf8ff",
                                                                        "protocol": "http://iiif.io/api/image",
                                                                        "height": 12054,
                                                                        "width": 18118,
                                                                        "profile": "http://iiif.io/api/image/2/level1.json"
                                                                }
                                                        },
                                                        "on": "https://dlc.services/iiif-query/7/?canvas=n2&manifest=s1&sequence=n1&s1=kalktekeningen&n1=&n2=5037"
                                                }
                                        ],
                                        "label": "Principe-details merbau kozijnen"
                                },
                                {
                                        "@id": "https://dlc.services/iiif-query/7/?canvas=n2&manifest=s1&sequence=n1&s1=kalktekeningen&n1=&n2=5038",
                                        "@type": "sc:Canvas",
                                        "thumbnail": {
                                                "@id": "https://dlc.services/thumbs/7/14/c2bb15c1-e849-49f7-9232-35c06de738ac/full/full/0/default.jpg",
                                                "@type": "dctypes:Image",
                                                "service": {
                                                        "@context": "http://iiif.io/api/image/2/context.json",
                                                        "@id": "https://apex.dlc.services/thumbs/7/14/c2bb15c1-e849-49f7-9232-35c06de738ac",
                                                        "profile": [
                                                                "http://iiif.io/api/image/2/level0.json",
                                                                {
                                                                        "formats": [
                                                                                "jpg"
                                                                        ],
                                                                        "qualities": [
                                                                                "color"
                                                                        ],
                                                                        "supports": [
                                                                                "sizeByWhListed"
                                                                        ]
                                                                }
                                                        ],
                                                        "width": 1024,
                                                        "height": 678,
                                                        "sizes": [
                                                                {
                                                                        "width": 1024,
                                                                        "height": 678
                                                                },
                                                                {
                                                                        "width": 400,
                                                                        "height": 265
                                                                },
                                                                {
                                                                        "width": 200,
                                                                        "height": 132
                                                                },
                                                                {
                                                                        "width": 100,
                                                                        "height": 66
                                                                }
                                                        ]
                                                }
                                        },
                                        "height": 11672,
                                        "width": 17624,
                                        "images": [
                                                {
                                                        "@id": "https://dlc.services/iiif-img/7/14/c2bb15c1-e849-49f7-9232-35c06de738ac/anno",
                                                        "@type": "oa:Annotation",
                                                        "motivation": "sc:painting",
                                                        "resource": {
                                                                "@id": "https://dlc.services/iiif-img/7/14/c2bb15c1-e849-49f7-9232-35c06de738ac/full/!2000,2000/0/default.jpg",
                                                                "@type": "dctypes:Image",
                                                                "height": 11672,
                                                                "width": 17624,
                                                                "service": {
                                                                        "@id": "https://dlc.services/iiif-img/7/14/c2bb15c1-e849-49f7-9232-35c06de738ac",
                                                                        "protocol": "http://iiif.io/api/image",
                                                                        "height": 11672,
                                                                        "width": 17624,
                                                                        "profile": "http://iiif.io/api/image/2/level1.json"
                                                                }
                                                        },
                                                        "on": "https://dlc.services/iiif-query/7/?canvas=n2&manifest=s1&sequence=n1&s1=kalktekeningen&n1=&n2=5038"
                                                }
                                        ],
                                        "label": "Overzicht binnenpuien -deuren en -kozijnen met principe-details"
                                }
                        ]
                }
        ]
}